gitspyx.py
gitspyx-2.2.0.dist-info/licenses/LICENSE
gitspyx-2.2.0.dist-info/METADATA
gitspyx-2.2.0.dist-info/WHEEL
gitspyx-2.2.0.dist-info/entry_points.txt
gitspyx-2.2.0.dist-info/top_level.txt
gitspyx-2.2.0.dist-info/RECORD
