Metadata-Version: 2.4
Name: gitspyx
Version: 2.2.0
Summary: Advanced GitHub Intelligence Tool - OSINT tool for GitHub reconnaissance
Home-page: https://github.com/VritraSecz/GitSpyX
Author: Alex Butler
License: MIT License
Project-URL: Homepage, https://github.com/VritraSecz/GitSpyX
Project-URL: Bug Reports, https://github.com/VritraSecz/GitSpyX/issues
Project-URL: Source, https://github.com/VritraSecz/GitSpyX
Project-URL: Documentation, https://github.com/VritraSecz/GitSpyX#readme
Keywords: osint,github,intelligence,reconnaissance,security,tool,cybersecurity
Classifier: Development Status :: 5 - Production/Stable
Classifier: Intended Audience :: Developers
Classifier: Intended Audience :: Information Technology
Classifier: Topic :: Security
Classifier: Topic :: Software Development :: Libraries :: Python Modules
Classifier: Topic :: System :: Networking
Classifier: Topic :: Internet :: WWW/HTTP :: Indexing/Search
Classifier: License :: OSI Approved :: MIT License
Classifier: Programming Language :: Python :: 3
Classifier: Programming Language :: Python :: 3.7
Classifier: Programming Language :: Python :: 3.8
Classifier: Programming Language :: Python :: 3.9
Classifier: Programming Language :: Python :: 3.10
Classifier: Programming Language :: Python :: 3.11
Classifier: Programming Language :: Python :: 3.12
Classifier: Operating System :: OS Independent
Requires-Python: >=3.7
License-File: LICENSE
Requires-Dist: rich>=12.0.0
Requires-Dist: requests>=2.25.1
Dynamic: home-page
Dynamic: license-file
Dynamic: requires-python
